sagemaker_jupyterlab_emr_extension/__init__.py
sagemaker_jupyterlab_emr_extension/_version.py
sagemaker_jupyterlab_emr_extension/clients.py
sagemaker_jupyterlab_emr_extension/constants.py
sagemaker_jupyterlab_emr_extension/converters.py
sagemaker_jupyterlab_emr_extension/handlers.py
sagemaker_jupyterlab_emr_extension/botocore_model/emrprivate/2016-07-07/paginators-1.json
sagemaker_jupyterlab_emr_extension/botocore_model/emrprivate/2016-07-07/service-2.json
sagemaker_jupyterlab_emr_extension/botocore_model/sagemaker/2017-07-24/service-2.json
sagemaker_jupyterlab_emr_extension/client/__init__.py
sagemaker_jupyterlab_emr_extension/client/emr_serverless_client.py
sagemaker_jupyterlab_emr_extension/converter/__init__.py
sagemaker_jupyterlab_emr_extension/converter/emr_serverless_converters.py
sagemaker_jupyterlab_emr_extension/handler/__init__.py
sagemaker_jupyterlab_emr_extension/handler/base_emr_handler.py
sagemaker_jupyterlab_emr_extension/handler/emr_serverless_handlers.py
sagemaker_jupyterlab_emr_extension/labextension/package.json
sagemaker_jupyterlab_emr_extension/labextension/static/122.da09b57160dcac90752d.js
sagemaker_jupyterlab_emr_extension/labextension/static/158.77f02e0e5a2c64044054.js
sagemaker_jupyterlab_emr_extension/labextension/static/171.65db3cdf4bdaecfcee27.js
sagemaker_jupyterlab_emr_extension/labextension/static/282.bf82b038bb65ae184032.js
sagemaker_jupyterlab_emr_extension/labextension/static/338.c78eb820c3664d6625d6.js
sagemaker_jupyterlab_emr_extension/labextension/static/338.c78eb820c3664d6625d6.js.LICENSE.txt
sagemaker_jupyterlab_emr_extension/labextension/static/378.86e6f59c2f75432fcd54.js
sagemaker_jupyterlab_emr_extension/labextension/static/486.a8e158cab70acb82c0ce.js
sagemaker_jupyterlab_emr_extension/labextension/static/486.a8e158cab70acb82c0ce.js.LICENSE.txt
sagemaker_jupyterlab_emr_extension/labextension/static/505.2d76192f6f70cae1b6dc.js
sagemaker_jupyterlab_emr_extension/labextension/static/567.2edf72cd29ecd4a06d5d.js
sagemaker_jupyterlab_emr_extension-0.4.3.dist-info/licenses/LICENSE
sagemaker_jupyterlab_emr_extension-0.4.3.dist-info/METADATA
sagemaker_jupyterlab_emr_extension-0.4.3.dist-info/WHEEL
sagemaker_jupyterlab_emr_extension-0.4.3.dist-info/top_level.txt
sagemaker_jupyterlab_emr_extension-0.4.3.dist-info/RECORD
