Metadata-Version: 2.4
Name: sagemaker-jupyterlab-emr-extension
Version: 0.4.3
Summary: SageMaker JupyterLab EMR extension
Home-page: https://aws.amazon.com/sagemaker/
Author: Amazon
License: Amazon Software License
Keywords: Jupyter,JupyterLab,JupyterLab4
Platform: Linux
Platform: Mac OS X
Platform: Windows
Classifier: Programming Language :: Python
Classifier: Programming Language :: Python :: 3
Classifier: Programming Language :: Python :: 3.9
Classifier: Framework :: Jupyter
Requires-Python: >=3.9
License-File: LICENSE
Requires-Dist: jupyterlab>=4
Requires-Dist: sagemaker_jupyterlab_extension_common>=0.2.10
Requires-Dist: jsonschema
Provides-Extra: dev
Requires-Dist: pytest>=6; extra == "dev"
Requires-Dist: pytest-cov; extra == "dev"
Requires-Dist: black; extra == "dev"
Requires-Dist: pytest-asyncio; extra == "dev"
Requires-Dist: pytest_jupyter; extra == "dev"
Dynamic: author
Dynamic: classifier
Dynamic: description
Dynamic: description-content-type
Dynamic: home-page
Dynamic: keywords
Dynamic: license
Dynamic: license-file
Dynamic: platform
Dynamic: provides-extra
Dynamic: requires-dist
Dynamic: requires-python
Dynamic: summary
